SignExt.v
`timescale 1ns / 1 ps

module SignExtender(BusImm, Imm, Ctrl); 
  output reg [63:0]  BusImm; 
  input [25:0] Imm; 
  input [1:0] Ctrl; 

  //wire extBit = 1'b0; 
  //assign #1 extBit = (Ctrl ? 1'b0 : Imm16[15]); 
  //assign BusImm = {{16{extBit}}, Imm16};

  //00: I-type, 01: D-type, 10: B, 11: CBZ
  always @ (*)
  begin
     case(Ctrl)
       0 : BusImm #1 <= {52'b0,Imm[21:10]};
       1 : BusImm #1 <= {{55{Imm[20]}},Imm[20:12]};
       2 : BusImm #1 <= {{36{Imm[25]}},Imm[25:0],2'b0};
       3 : BusImm #1 <= {{43{Imm[23]}},Imm[23:5],2'b0};
     endcase // case (Ctrl)
  end

 

endmodule

SignExtTest.v
`timescale 1ns / 1ps

////////////////////////////////////////////////////////////////////////////////
// Company: 
// Engineer:
//
// Create Date:   15:06:33 03/02/2009
// Design Name:   Decode24
// Module Name:   E:/350/ECEN_350_Labs/ECEN350_RasPI/Lab07/SignExtender/SignExt.v
// Project Name:  SignExt
// Target Device:  
// Tool versions:  
// Description: 
//
// Verilog Test Fixture created by ISE for module: Decode24
//
// Dependencies:
// 
// Revision:
// Revision 0.01 - File Created
// Additional Comments:
// 
////////////////////////////////////////////////////////////////////////////////

`define STRLEN 15
module SignExtTest_v;

	initial //This initial block used to dump all wire/reg values to dump file
     begin
       $dumpfile("SignExt.vcd");
       $dumpvars(0,SignExtTest_v);
     end

	task passTest;
		input [63:0] actualOut, expectedOut;
		input [`STRLEN*8:0] testType;
		inout [7:0] passed;
	
		if(actualOut == expectedOut) begin $display ("%s passed", testType); passed = passed + 1; end
		else $display ("%s failed: %d should be %d", testType, actualOut, expectedOut);
	endtask
	
	task allPassed;
		input [7:0] passed;
		input [7:0] numTests;
		
		if(passed == numTests) $display ("All tests passed");
		else $display("Some tests failed");
	endtask // allPassed

   	task stim;
		input [25:0] newImm;
		input [1:0] newCtrl;
		output [25:0] setImm;
		output [1:0] setCtrl;
		
		begin
			#90;
			setImm = newImm;
			setCtrl = newCtrl;
		end
	endtask
	
	// Inputs
	reg [25:0] Imm;
        reg [1:0] Ctrl;
	reg [7:0] passed;

	// Outputs
	wire [63:0] BusImm;
        wire [63:0] I = {52'b0,Imm[21:10]};
        wire [63:0] D = {{55{Imm[20]}}, Imm[20:12]};
        wire [63:0] B = {{36{Imm[25]}}, Imm[25:0], 2'b0};
        wire [63:0] CBZ = {{43{Imm[23]}}, Imm[23:5], 2'b0};
        wire [25:0] test = 26'b10101010101010101010101010;
   

	// Instantiate the Unit Under Test (UUT)
	SignExtender uut (
		.BusImm(BusImm), 
		.Imm(Imm),
		.Ctrl(Ctrl)     
	);

	initial begin
		// Initialize Inputs
		Imm = 0;
	        Ctrl = 0;
		passed = 0;


		// Add stimulus here
	   stim(test, 2'b00, Imm, Ctrl); #10; passTest(BusImm, I, "Input 0", passed);
	   stim(test, 2'b01, Imm, Ctrl); #10; passTest(BusImm, D, "Input 1", passed);
	   stim(test, 2'b10, Imm, Ctrl); #10; passTest(BusImm, B, "Input 2", passed);
	   stim(test, 2'b11, Imm, Ctrl); #10; passTest(BusImm, CBZ, "Input 3", passed);
		#90;
		
		allPassed(passed, 4);

	end
      
endmodule

SignExt.vcd
$date
	Thu Nov  4 15:38:49 2021
$end
$version
	Icarus Verilog
$end
$timescale
	1ps
$end
$scope module SignExtTest_v $end
$var wire 26 ! test [25:0] $end
$var wire 64 " I [63:0] $end
$var wire 64 # D [63:0] $end
$var wire 64 $ CBZ [63:0] $end
$var wire 64 % BusImm [63:0] $end
$var wire 64 & B [63:0] $end
$var reg 2 ' Ctrl [1:0] $end
$var reg 26 ( Imm [25:0] $end
$var reg 8 ) passed [7:0] $end
$scope module uut $end
$var wire 2 * Ctrl [1:0] $end
$var wire 26 + Imm [25:0] $end
$var reg 64 , BusImm [63:0] $end
$upscope $end
$scope task allPassed $end
$var reg 8 - numTests [7:0] $end
$var reg 8 . passed [7:0] $end
$upscope $end
$scope task passTest $end
$var reg 64 / actualOut [63:0] $end
$var reg 64 0 expectedOut [63:0] $end
$var reg 8 1 passed [7:0] $end
$var reg 121 2 testType [120:0] $end
$upscope $end
$scope task stim $end
$var reg 2 3 newCtrl [1:0] $end
$var reg 26 4 newImm [25:0] $end
$var reg 2 5 setCtrl [1:0] $end
$var reg 26 6 setImm [25:0] $end
$upscope $end
$upscope $end
$enddefinitions $end
#0
$dumpvars
bx 6
bx 5
b10101010101010101010101010 4
b0 3
bx 2
bx 1
bx 0
bx /
bx .
bx -
b0 ,
b0 +
b0 *
b0 )
b0 (
b0 '
b0 &
b0 %
b0 $
b0 #
b0 "
b10101010101010101010101010 !
$end
#90000
b101010101010 %
b101010101010 ,
b101010101010 "
b10101010 #
b1111111111111111111111111111111111111111111101010101010101010100 $
b1111111111111111111111111111111111111010101010101010101010101000 &
b10101010101010101010101010 (
b10101010101010101010101010 +
b0 5
b10101010101010101010101010 6
#100000
b1 3
b1 )
b1 1
b1001001011011100111000001110101011101000010000000110000 2
b101010101010 0
b101010101010 /
#190000
b10101010 %
b10101010 ,
b1 '
b1 *
b1 5
#200000
b10 3
b10 )
b10 1
b1001001011011100111000001110101011101000010000000110001 2
b10101010 0
b10101010 /
#290000
b1111111111111111111111111111111111111010101010101010101010101000 %
b1111111111111111111111111111111111111010101010101010101010101000 ,
b10 '
b10 *
b10 5
#300000
b11 3
b11 )
b11 1
b1001001011011100111000001110101011101000010000000110010 2
b1111111111111111111111111111111111111010101010101010101010101000 0
b1111111111111111111111111111111111111010101010101010101010101000 /
#390000
b1111111111111111111111111111111111111111111101010101010101010100 %
b1111111111111111111111111111111111111111111101010101010101010100 ,
b11 '
b11 *
b11 5
#400000
b100 )
b100 1
b1001001011011100111000001110101011101000010000000110011 2
b1111111111111111111111111111111111111111111101010101010101010100 0
b1111111111111111111111111111111111111111111101010101010101010100 /
#490000
b100 -
b100 .
